MANIFEST.in
README.md
setup.py
src/EVE_SRP.egg-info/PKG-INFO
src/EVE_SRP.egg-info/SOURCES.txt
src/EVE_SRP.egg-info/dependency_links.txt
src/EVE_SRP.egg-info/entry_points.txt
src/EVE_SRP.egg-info/not-zip-safe
src/EVE_SRP.egg-info/requires.txt
src/EVE_SRP.egg-info/top_level.txt
src/evesrp/__init__.py
src/evesrp/default_config.py
src/evesrp/json.py
src/evesrp/killmail.py
src/evesrp/models.py
src/evesrp/ships.py
src/evesrp/static_data.py
src/evesrp/systems.py
src/evesrp/transformers.py
src/evesrp/versioned_static.py
src/evesrp/auth/__init__.py
src/evesrp/auth/bravecore.py
src/evesrp/auth/evesso.py
src/evesrp/auth/j4oauth.py
src/evesrp/auth/models.py
src/evesrp/auth/oauth.py
src/evesrp/auth/testauth.py
src/evesrp/auth/testoauth.py
src/evesrp/migrate/__init__.py
src/evesrp/migrate/alembic.ini
src/evesrp/migrate/env.py
src/evesrp/migrate/script.py.mako
src/evesrp/migrate/versions/108d7a5881c7_.py
src/evesrp/migrate/versions/19506187e7aa_add_a_full_text_search_index_for_mysql.py
src/evesrp/migrate/versions/2976d59f286_.py
src/evesrp/migrate/versions/2f22504b1e6_.py
src/evesrp/migrate/versions/337978f8c75_restrict_request_base_payout_to_be_0.py
src/evesrp/migrate/versions/3d35f833a24_.py
src/evesrp/migrate/versions/3e5e1d3a02c_denormalize_request_payout.py
src/evesrp/migrate/versions/3f453bb4f2d7_discern_between_access_and_refresh_.py
src/evesrp/migrate/versions/4198a248c8a_.py
src/evesrp/migrate/versions/4280bf2417c_.py
src/evesrp/migrate/versions/45024170cf6_rename_action__type_to_action_type_.py
src/evesrp/migrate/versions/5795c29b2c7a_.py
src/evesrp/migrate/versions/8f179e969c9_add_an_auditor_level_permission.py
src/evesrp/migrate/versions/__init__.py
src/evesrp/migrate/versions/c1fc69b629_.py
src/evesrp/migrate/versions/e6b2c156b11_allow_pilots_to_not_have_owning_users.py
src/evesrp/static/ZeroClipboard.swf
src/evesrp/static/evesso.png
src/evesrp/static/favicon.ico
src/evesrp/static/css/evesrp.css
src/evesrp/static/css/evesrp.css.map
src/evesrp/static/fonts/FontAwesome.otf
src/evesrp/static/fonts/fontawesome-webfont.eot
src/evesrp/static/fonts/fontawesome-webfont.svg
src/evesrp/static/fonts/fontawesome-webfont.ttf
src/evesrp/static/fonts/fontawesome-webfont.woff
