Metadata-Version: 1.1
Name: EVE-SRP
Version: 0.12.11
Summary: EVE Ship Replacement Program Helper
Home-page: https://github.com/paxswill/evesrp
Author: Will Ross
Author-email: paxswill@paxswill.com
License: BSD
Platform: UNKNOWN
Classifier: Development Status :: 4 - Beta
Classifier: Framework :: Flask
Classifier: License :: OSI Approved :: BSD License
Classifier: Programming Language :: Python :: 3
Classifier: Programming Language :: Python :: 2
Classifier: Topic :: Games/Entertainment
